aa.py
canvas.py
test.py
threedplot.py
uievent.py
util_func.py
xxx.py
difdyf/__init__.py
difdyf/plotfig.py
difdyf/util_func.py
difdyf-1.14112.dist-info/METADATA
difdyf-1.14112.dist-info/WHEEL
difdyf-1.14112.dist-info/top_level.txt
difdyf-1.14112.dist-info/RECORD
