Metadata-Version: 2.1
Name: difdyf
Version: 1.14112
Summary: A  module for diff geo
Home-page: https://github.com/yftheone1995/dyf@riec.tohoku.ac.jp
Author: dyf
Author-email: 715017912@qq.com
License: MIT
Platform: UNKNOWN
Requires: numpy
Requires: sympy
